faeruniancalendar/__init__.py
faeruniancalendar/converter.py
faeruniancalendar/data/__init__.py
faeruniancalendar/data/common_year.py
faeruniancalendar/data/leap_year.py
faeruniancalendar-1.0.0.dist-info/METADATA
faeruniancalendar-1.0.0.dist-info/WHEEL
faeruniancalendar-1.0.0.dist-info/licenses/LICENSE
faeruniancalendar-1.0.0.dist-info/RECORD
