Metadata-Version: 2.1
Name: faeruniancalendar
Version: 1.0.0
Summary: A Python module for calculating Faerunian date information based on the Gregorian calendar.
Project-URL: Homepage, https://github.com/sebastianbingham/faeruniancalendar-python
Project-URL: Issues, https://github.com/sebastianbingham/faeruniancalendar-python/issues
Project-URL: Repository, https://github.com/sebastianbingham/faeruniancalendar-python.git
Author-email: Sebastian Bingham <sebastian@sebastianbingham.com>
License: ## MIT License
License-File: LICENSE
Keywords: date calculation,faerun,faerunian
Classifier: Development Status :: 4 - Beta
Classifier: Intended Audience :: Developers
Classifier: License :: OSI Approved :: MIT License
Classifier: Operating System :: OS Independent
Classifier: Programming Language :: Python :: 3
Classifier: Programming Language :: Python :: 3.6
Classifier: Programming Language :: Python :: 3.7
Classifier: Programming Language :: Python :: 3.8
Classifier: Programming Language :: Python :: 3.9
Classifier: Programming Language :: Python :: 3.10
Classifier: Programming Language :: Python :: 3.11
Requires-Python: >=3
